[
    {
        "id": 1,
        "x1": 3,
        "y1": 30,
        "x2": 2,
        "y2": 64,
        "x3": 1.5,
        "y3": 40
    },
    {
        "id": 2,
        "x1": 3,
        "y1": 90,
        "x2": 4,
        "y2": 41,
        "x3": 3.2,
        "y3": 80
    },
    {
        "id": 3,
        "x1": 4,
        "y1": 74,
        "x2": 6,
        "y2": 36,
        "x3": 2.1,
        "y3": 20
    },
    {
        "id": 4,
        "x1": 5,
        "y1": 43,
        "x2": 3,
        "y2": 22,
        "x3": 0.7,
        "y3": 90
    },
    {
        "id": 5,
        "x1": 1,
        "y1": 32,
        "x2": 7,
        "y2": 57,
        "x3": 4.8,
        "y3": 50
    },
    {
        "id": 6,
        "x1": 7,
        "y1": 21,
        "x2": 1,
        "y2": 71,
        "x3": 2.4,
        "y3": 70
    },
    {
        "id": 7,
        "x1": 6,
        "y1": 81,
        "x2": 8,
        "y2": 18,
        "x3": 4.3,
        "y3": 30
    },
    {
        "id": 8,
        "x1": 8,
        "y1": 55,
        "x2": 5,
        "y2": 51,
        "x3": 0.5,
        "y3": 10
    },
    {
        "id": 9,
        "x1": 9,
        "y1": 15,
        "x2": 9,
        "y2": 39,
        "x3": 3.9,
        "y3": 60
    },
    {
        "id": 10,
        "x1": 10,
        "y1": 23,
        "x2": 3,
        "y2": 40,
        "x3": 1.8,
        "y3": 10
    }
]